pyagnostics/__init__.py
pyagnostics/_test.py
pyagnostics/exceptions.py
pyagnostics/protocols.py
pyagnostics/py.typed
pyagnostics/report.py
pyagnostics/severity.py
pyagnostics/source.py
pyagnostics/spans.py
pyagnostics-3.0.0.dist-info/METADATA
pyagnostics-3.0.0.dist-info/WHEEL
pyagnostics-3.0.0.dist-info/licenses/LICENSE
pyagnostics-3.0.0.dist-info/RECORD
