Metadata-Version: 2.4
Name: pyagnostics
Version: 3.0.0
Summary: 
License-Expression: MIT
License-File: LICENSE
Author: RISQ Capital
Author-email: dev@risqcapital.com
Requires-Python: >=3.11,<4
Classifier: Programming Language :: Python :: 3
Classifier: Programming Language :: Python :: 3.11
Classifier: Programming Language :: Python :: 3.12
Classifier: Programming Language :: Python :: 3.13
Classifier: Programming Language :: Python :: 3.14
Requires-Dist: rich (>=13,<15)
Project-URL: Bug Tracker, https://github.com/risqcapital/pyagnostics/issues
Project-URL: Repository, https://github.com/risqcapital/pyagnostics
